LICENSE.txt
MANIFEST.in
README.rst
setup.py
django_realestate.egg-info/PKG-INFO
django_realestate.egg-info/SOURCES.txt
django_realestate.egg-info/dependency_links.txt
django_realestate.egg-info/requires.txt
django_realestate.egg-info/top_level.txt
docs/index.rst
realestate/__init__.py
realestate/context_processors.py
realestate/search_indexes.py
realestate/urls.py
realestate/admin/__init__.py
realestate/admin/forms.py
realestate/admin/models.py
realestate/admin/tests.py
realestate/admin/urls.py
realestate/admin/views.py
realestate/api/__init__.py
realestate/api/authentication.py
realestate/api/models.py
realestate/api/serializers.py
realestate/api/urls.py
realestate/api/views.py
realestate/api/migrations/0001_initial.py
realestate/api/migrations/0002_auto__add_field_apikeys_description.py
realestate/api/migrations/__init__.py
realestate/home/__init__.py
realestate/home/models.py
realestate/home/tests.py
realestate/home/views.py
realestate/home/templatetags/__init__.py
realestate/home/templatetags/home_widgets.py
realestate/home/templatetags/re_paginator.py
realestate/listing/__init__.py
realestate/listing/admin.py
realestate/listing/forms.py
realestate/listing/models.py
realestate/listing/sitemap.py
realestate/listing/tests.py
realestate/listing/utils.py
realestate/listing/views.py
realestate/listing/fixtures/attributes.json
realestate/listing/migrations/0001_initial.py
realestate/listing/migrations/0002_auto__add_field_onsale_price_currency__add_field_onsale_price.py
realestate/listing/migrations/0003_auto__del_sector__add_location__add_deal__del_field_listing_sector__ad.py
realestate/listing/migrations/0004_auto__chg_field_location_parent.py
realestate/listing/migrations/0005_auto__add_field_attributelisting_order.py
realestate/listing/migrations/0006_auto__add_field_agent_first_name__add_field_agent_last_name__chg_field.py
realestate/listing/migrations/__init__.py
realestate/listing/templatetags/__init__.py
realestate/listing/templatetags/extra_functions.py
realestate/locale/es/LC_MESSAGES/django.po
realestate/static/admin/css/AdminLTE.css
realestate/static/admin/css/editForms.css
realestate/static/admin/img/ajax-loader.gif
