Metadata-Version: 1.1
Name: django-realestate
Version: 1.5.0
Summary: Real Estate app built on Django
Home-page: https://github.com/wm3ndez/realestate
Author: Williams Mendez
Author-email: wmendez27@gmail.com
License: Copyright (c) 2014, Williams Méndez.
